backend/debug_run.py
backend/core/__init__.py
backend/core/case_utils.py
backend/core/combiner.py
backend/core/converter.py
backend/core/enricher.py
backend/core/enricher_switch.py
backend/core/extractor.py
backend/utils/__init__.py
backend/utils/compressor.py
backend/utils/converter_match.py
backend/utils/converter_validation.py
backend/utils/encryptor.py
backend/utils/extractor_validation.py
cijferho/__init__.py
1cijferho-0.1.0.dist-info/METADATA
1cijferho-0.1.0.dist-info/WHEEL
1cijferho-0.1.0.dist-info/RECORD
