Metadata-Version: 2.4
Name: 1cijferho
Version: 0.1.0
Summary: Professional tools for processing Dutch higher educational data (1CijferHO / ROD)
Project-URL: Homepage, https://github.com/cedanl/1cijferho
Project-URL: Repository, https://github.com/cedanl/1cijferho.git
Project-URL: Issues, https://github.com/cedanl/1cijferho/issues
License: MIT
Keywords: data-processing,duo,education,higher-education,netherlands
Classifier: Development Status :: 4 - Beta
Classifier: Intended Audience :: Education
Classifier: Intended Audience :: Science/Research
Classifier: License :: OSI Approved :: MIT License
Classifier: Programming Language :: Python :: 3.13
Classifier: Topic :: Education
Requires-Python: >=3.13
Requires-Dist: fastexcel>=0.12.1
Requires-Dist: numpy>=2.2.2
Requires-Dist: openpyxl>=3.1.5
Requires-Dist: pandas>=2.2.3
Requires-Dist: plotly>=6.0.0
Requires-Dist: polars>=1.21.0
Requires-Dist: pyyaml>=6.0.0
Requires-Dist: rich>=13.9.4
Requires-Dist: ruff>=0.10.0
Requires-Dist: streamlit-extras>=0.6.0
Requires-Dist: streamlit>=1.41.1
Requires-Dist: xlsxwriter>=3.2.2
